{
  "gitSyncId": "6808fda53361a34d8231cac0_4f0bbecb-4299-4f3f-bc40-f6bb25da3007",
  "id": "Home_getPeriodo",
  "pluginId": "google-sheets-plugin",
  "pluginType": "SAAS",
  "unpublishedAction": {
    "actionConfiguration": {
      "encodeParamsToggle": true,
      "formData": {
        "command": {
          "data": "FETCH_MANY"
        },
        "entityType": {
          "data": "ROWS"
        },
        "pagination": {
          "data": {
            "limit": "1",
            "offset": "0"
          }
        },
        "projection": {
          "data": []
        },
        "queryFormat": {
          "data": "ROWS"
        },
        "range": {
          "data": ""
        },
        "sheetName": {
          "data": "periodi"
        },
        "sheetUrl": {
          "componentData": "",
          "data": "https://docs.google.com/spreadsheets/d/186jsr4bHqJ60W8_WEg_RJdu14jYVQ6RI8VRNVe80gWg",
          "viewType": "json"
        },
        "smartSubstitution": {
          "data": true
        },
        "sortBy": {
          "data": [
            {
              "column": "data_inizio",
              "order": "Ascending"
            }
          ]
        },
        "tableHeaderIndex": {
          "data": "1"
        },
        "where": {
          "data": {
            "children": [
              {
                "condition": "LTE",
                "key": "data_inizio",
                "value": "{{moment().format('YYYY-MM-DD')}}"
              },
              {
                "condition": "GTE",
                "key": "data_fine",
                "value": "{{moment().format('YYYY-MM-DD')}}"
              },
              {
                "children": [
                  {
                    "condition": "EQ",
                    "key": "disabilitato"
                  },
                  {
                    "condition": "NOT_IN",
                    "key": "disabilitato",
                    "value": "{{['si']}}"
                  }
                ],
                "condition": "OR"
              }
            ],
            "condition": "AND"
          }
        }
      },
      "paginationType": "NONE",
      "timeoutInMillisecond": 10000
    },
    "confirmBeforeExecute": false,
    "datasource": {
      "id": "gpsvar_data",
      "isAutoGenerated": false,
      "name": "gpsvar_data",
      "pluginId": "google-sheets-plugin"
    },
    "dynamicBindingPathList": [
      {
        "key": "formData.where.data.children[0].value"
      },
      {
        "key": "formData.where.data.children[1].value"
      },
      {
        "key": "formData.where.data.children[2].children[1].value"
      }
    ],
    "name": "getPeriodo",
    "pageId": "Home",
    "runBehaviour": "MANUAL",
    "userSetOnLoad": true
  }
}